pyroll/report/__init__.py
pyroll/report/cli.py
pyroll/report/config.py
pyroll/report/hookspecs.py
pyroll/report/main.html
pyroll/report/pluggy.py
pyroll/report/report.py
pyroll/report/utils.py
pyroll/report/unit_display/__init__.py
pyroll/report/unit_display/format.py
pyroll/report/unit_display/format_guards.py
pyroll/report/unit_display/format_special_numbers.py
pyroll/report/unit_display/plots.html
pyroll/report/unit_display/plots.py
pyroll/report/unit_display/properties.html
pyroll/report/unit_display/properties.py
pyroll/report/unit_display/units.py
pyroll_report-3.1.0.dist-info/METADATA
pyroll_report-3.1.0.dist-info/WHEEL
pyroll_report-3.1.0.dist-info/entry_points.txt
pyroll_report-3.1.0.dist-info/licenses/LICENSE
pyroll_report-3.1.0.dist-info/RECORD
